MANIFEST.in
README.rst
setup.cfg
setup.py
pretend_extended/__init__.py
pretend_extended3.egg-info/PKG-INFO
pretend_extended3.egg-info/SOURCES.txt
pretend_extended3.egg-info/dependency_links.txt
pretend_extended3.egg-info/requires.txt
pretend_extended3.egg-info/top_level.txt
pretend_extended/client/__init__.py
pretend_extended/client/http.py
pretend_extended/client/smtp.py
pretend_extended/common/__init__.py
pretend_extended/common/constants.py
pretend_extended/common/exceptions.py
pretend_extended/common/http.py
pretend_extended/common/pretender.py
pretend_extended/common/smtp.py
pretend_extended/common/compat/__init__.py
pretend_extended/common/compat/dictconfig.py
pretend_extended/common/compat/ordered_dict.py
pretend_extended/common/tests/__init__.py
pretend_extended/common/tests/test_match_rule.py
pretend_extended/server/__init__.py
pretend_extended/server/base.py
pretend_extended/server/data.py
pretend_extended/server/log.py
pretend_extended/server/maintain.py
pretend_extended/server/middleware.py
pretend_extended/server/pretender.py
pretend_extended/server/server.py
pretend_extended/server/settings.py
pretend_extended/server/utils.py
pretend_extended/server/views.py
pretend_extended/server/apps/__init__.py
pretend_extended/server/apps/history.py
pretend_extended/server/apps/preset.py
pretend_extended/server/apps/pretender.py
pretend_extended/server/apps/replay.py
pretend_extended/server/mock_servers/__init__.py
pretend_extended/server/mock_servers/http/__init__.py
pretend_extended/server/mock_servers/http/handler.py
pretend_extended/server/mock_servers/smtp/__init__.py
pretend_extended/server/mock_servers/smtp/handler.py
pretend_extended/server/mock_servers/smtp/server.py
pretend_extended/server/mock_servers/ssh/__init__.py
pretend_extended/server/mock_servers/ssh/server.py
tests/__init__.py
tests/integration/__init__.py
tests/integration/test_http.py
tests/integration/test_maintenance.py
tests/integration/test_multiple_mock_servers.py
tests/integration/test_named_mock_servers.py
tests/integration/test_preset.py
tests/integration/test_smtp.py