Metadata-Version: 1.1
Name: pretend-extended3
Version: 3.0
Summary: Fake servers for testing
Home-page: https://github.com/sheltonpaul89/pretender-extn3
Author: Shelton Paul Infant
Author-email: sheltonpaul89@gmail.com
License: UNKNOWN
Download-URL: https://github.com/sheltonpaul89/pretender-extn3/tarball/3.0
Platform: UNKNOWN
Classifier: Development Status :: 4 - Beta
Classifier: Environment :: Console
Classifier: Intended Audience :: Developers
Classifier: License :: OSI Approved :: GNU Library or Lesser General Public License (LGPL)
Classifier: Operating System :: OS Independent
Classifier: Programming Language :: Python :: 3
Classifier: Topic :: Software Development :: Testing
